discobiscuit/__init__.py
discobiscuit/__main__.py
discobiscuit/clients.py
discobiscuit/exceptions.py
discobiscuit/models/__init__.py
discobiscuit/models/auth.py
discobiscuit/models/mes.py
discobiscuit/models/responses.py
discobiscuit/models/test.py
discobiscuit-0.2.0.dist-info/METADATA
discobiscuit-0.2.0.dist-info/WHEEL
discobiscuit-0.2.0.dist-info/licenses/LICENSE
discobiscuit-0.2.0.dist-info/RECORD
