Metadata-Version: 2.1
Name: discobiscuit
Version: 0.2.0
Summary: A wrapper around Middleman API
Author-email: Lauri Maertin <Lauri.Maertin@gmail.com>
License-File: LICENSE
Classifier: License :: OSI Approved :: MIT License
Classifier: Operating System :: OS Independent
Classifier: Programming Language :: Python :: 3
Requires-Python: >3.11
Requires-Dist: httpx>=0.25.1
Requires-Dist: pydantic>=2.4.2
Provides-Extra: dev
Requires-Dist: black; extra == 'dev'
Requires-Dist: bumpver; extra == 'dev'
Requires-Dist: isort; extra == 'dev'
Requires-Dist: pip-tools; extra == 'dev'
Requires-Dist: pytest; extra == 'dev'
